pytyper/.DS_Store
pytyper/__init__.py
pytyper/core/.DS_Store
pytyper/core/__init__.py
pytyper/core/calculation.py
pytyper/core/comparison.py
pytyper/core/exceptions.py
pytyper/core/formatting.py
pytyper/core/managers/.DS_Store
pytyper/core/managers/SessionData.py
pytyper/core/managers/TestData.py
pytyper/core/managers/__init__.py
pytyper/tests/.DS_Store
pytyper/tests/test_calculation.py
pytyper/tests/test_comparison.py
pytyper/tests/test_exceptions.py
pytyper/tests/test_formatting.py
pytyper/tests/managers/test_SessionData.py
pytyper/tests/managers/test_TestData.py
pytyper-0.1.3.dist-info/LICENSE
pytyper-0.1.3.dist-info/METADATA
pytyper-0.1.3.dist-info/WHEEL
pytyper-0.1.3.dist-info/top_level.txt
pytyper-0.1.3.dist-info/RECORD
