Metadata-Version: 2.1
Name: pytyper
Version: 0.1.3
Summary: Typing statistics calculations, string comparison, and formatting
Home-page: https://github.com/greysonDEV/pytyper
Author: Greyson Murray
Author-email: greysonmurray.dev@gmail.com
License: MIT
Platform: UNKNOWN
Classifier: License :: OSI Approved :: MIT License
Classifier: Programming Language :: Python :: 3.8
Classifier: Topic :: Games/Entertainment
Classifier: Operating System :: MacOS
Classifier: Intended Audience :: Developers
Classifier: Intended Audience :: Education
Classifier: Natural Language :: English
Requires-Python: >=3.8
